docs/conf.py
docs/run_notebooks.py
ross/__init__.py
ross/available_materials.toml
ross/bearing_seal_element.py
ross/conftest.py
ross/coupling_element.py
ross/disk_element.py
ross/element.py
ross/gear_element.py
ross/materials.py
ross/model_reduction.py
ross/multi_rotor.py
ross/new_units.txt
ross/plotly_theme.py
ross/point_mass.py
ross/probe.py
ross/results.py
ross/rotor_assembly.py
ross/shaft_element.py
ross/units.py
ross/utils.py
ross/assets/default.css
ross/assets/plot_with_mode_shape.css
ross/bearings/__init__.py
ross/bearings/fluid_flow.py
ross/bearings/fluid_flow_coefficients.py
ross/bearings/fluid_flow_geometry.py
ross/bearings/fluid_flow_graphics.py
ross/bearings/lubricants.py
ross/bearings/plain_journal.py
ross/bearings/thrust_pad.py
ross/bearings/tilting_pad.py
ross/benchmark/run_benchmarks.py
ross/faults/__init__.py
ross/faults/crack.py
ross/faults/misalignment.py
ross/faults/rubbing.py
ross/faults/data/PAPADOPOULOS.csv
ross/seals/__init__.py
ross/seals/holepattern_seal.py
ross/seals/labyrinth_seal.py
ross/stochastic/__init__.py
ross/stochastic/st_bearing_seal_element.py
ross/stochastic/st_disk_element.py
ross/stochastic/st_materials.py
ross/stochastic/st_point_mass.py
ross/stochastic/st_results.py
ross/stochastic/st_results_elements.py
ross/stochastic/st_rotor_assembly.py
ross/stochastic/st_shaft_element.py
ross/tests/frf.toml
ross/tests/test_6dof_model.py
ross/tests/test_bearing_seal_element.py
ross/tests/test_crack.py
ross/tests/test_disk_element.py
ross/tests/test_examples.py
ross/tests/test_fluid_flow.py
ross/tests/test_gear_element.py
ross/tests/test_holepattern.py
ross/tests/test_labyrinth.py
ross/tests/test_materials.py
ross/tests/test_misalignment.py
ross/tests/test_multi_rotor.py
ross/tests/test_plain_journal.py
ross/tests/test_point_mass.py
ross/tests/test_probe.py
ross/tests/test_results.py
ross/tests/test_rotor_assembly.py
ross/tests/test_rubbing.py
ross/tests/test_shaft_element.py
ross/tests/test_stochastic_elements.py
ross_rotordynamics-2.0.0.dist-info/licenses/LICENSE.md
ross_rotordynamics-2.0.0.dist-info/METADATA
ross_rotordynamics-2.0.0.dist-info/WHEEL
ross_rotordynamics-2.0.0.dist-info/top_level.txt
ross_rotordynamics-2.0.0.dist-info/RECORD
