Metadata-Version: 2.4
Name: ross-rotordynamics
Version: 2.0.0
Summary: ROSS: Rotordynamic Open Source Software
Author: ROSS developers
Author-email: Raphael Timbo Silva <raphaelts@petrobras.com.br>
Maintainer-email: Vinicius Teixeira da Costa <viniciustx@ufu.br>, Jessica Guarato de Freitas Santos <jessica.guarato@ufu.br>
License:                                  Apache License
Project-URL: Homepage, https://ross.readthedocs.io/
Project-URL: Documentation, https://ross.readthedocs.io/en/stable/
Project-URL: Repository, https://github.com/petrobras/ross
Project-URL: Discussions, https://github.com/petrobras/ross/discussions
Project-URL: Issues, https://github.com/petrobras/ross/issues
Classifier: License :: OSI Approved :: Apache Software License
Classifier: Programming Language :: Python
Classifier: Programming Language :: Python :: 3
Classifier: Programming Language :: Python :: 3.9
Classifier: Programming Language :: Python :: 3.10
Classifier: Programming Language :: Python :: 3.11
Classifier: Programming Language :: Python :: 3.12
Classifier: Programming Language :: Python :: Implementation :: CPython
Requires-Python: >=3.9
License-File: LICENSE.md
Requires-Dist: numpy
Requires-Dist: scipy
Requires-Dist: toml>=0.10.1
Requires-Dist: pandas>=0.23
Requires-Dist: plotly>=4.7.0
Requires-Dist: xlrd
Requires-Dist: pint>=0.18
Requires-Dist: methodtools
Requires-Dist: numba
Requires-Dist: ccp-performance
Requires-Dist: prettytable
Provides-Extra: dev
Requires-Dist: pytest>=4.6; extra == "dev"
Requires-Dist: pytest-cov; extra == "dev"
Requires-Dist: coverage; extra == "dev"
Requires-Dist: codecov; extra == "dev"
Requires-Dist: sphinx; extra == "dev"
Requires-Dist: myst-nb; extra == "dev"
Requires-Dist: sphinx-book-theme; extra == "dev"
Requires-Dist: sphinx-panels; extra == "dev"
Requires-Dist: sphinx-copybutton; extra == "dev"
Requires-Dist: sphinx-rtd-theme; extra == "dev"
Requires-Dist: linkify-it-py; extra == "dev"
Requires-Dist: numpydoc; extra == "dev"
Requires-Dist: sphinxcontrib-bibtex>=2.2; extra == "dev"
Requires-Dist: ruff; extra == "dev"
Requires-Dist: sphinx-design; extra == "dev"
Dynamic: license-file
